{
  "required": true,
  "minVersion": "0.8",
  "package": "net.asodev.islandutils.mixins",
  "compatibilityLevel": "JAVA_17",
  "mixins": [
    "cosmetics.ChestScreenMixin",
    "cosmetics.FontLoaderMixin",
    "discord.ConnectionMixin",
    "discord.PlayerTeamMixin",
    "resources.PackRepositoryMixin",
    "sounds.SoundSourceMixin"
  ],
  "client": [
    "ChatScreenMixin",
    "MainScreenMixin",
    "OptionsMixin",
    "PacketListenerMixin",
    "PauseScreenMixin",
    "accessors.SoundEngineAccessor",
    "accessors.SoundManagerAccessor",
    "cosmetics.UIMixin",
    "discord.JoinMCCIMixin",
    "resources.MultiplayerJoinMixin",
    "resources.ProgressScreenAccessor",
    "sounds.SoundOptionsMixin",
    "ui.CommandSuggestionsAccessor"
  ],
  "injectors": {
    "defaultRequire": 1
  }
}
